<annotation>
	<folder></folder>
	<filename>Navid_178_jpg.rf.536c1cad199b07116a6c16d99ee95e69.jpg</filename>
	<path>Navid_178_jpg.rf.536c1cad199b07116a6c16d99ee95e69.jpg</path>
	<source>
		<database>roboflow.ai</database>
	</source>
	<size>
		<width>640</width>
		<height>640</height>
		<depth>3</depth>
	</size>
	<segmented>0</segmented>
	<object>
		<name>vehicle</name>
		<pose>Unspecified</pose>
		<truncated>0</truncated>
		<difficult>0</difficult>
		<occluded>0</occluded>
		<bndbox>
			<xmin>182</xmin>
			<xmax>216</xmax>
			<ymin>280</ymin>
			<ymax>345</ymax>
		</bndbox>
	</object>
	<object>
		<name>vehicle</name>
		<pose>Unspecified</pose>
		<truncated>0</truncated>
		<difficult>0</difficult>
		<occluded>0</occluded>
		<bndbox>
			<xmin>228</xmin>
			<xmax>283</xmax>
			<ymin>205</ymin>
			<ymax>349</ymax>
		</bndbox>
	</object>
	<object>
		<name>vehicle</name>
		<pose>Unspecified</pose>
		<truncated>0</truncated>
		<difficult>0</difficult>
		<occluded>0</occluded>
		<bndbox>
			<xmin>285</xmin>
			<xmax>640</xmax>
			<ymin>1</ymin>
			<ymax>639</ymax>
		</bndbox>
	</object>
</annotation>
