<annotation>
	<folder></folder>
	<filename>Navid_792_jpg.rf.387fc93c6677f4bd2c410716b15d1951.jpg</filename>
	<path>Navid_792_jpg.rf.387fc93c6677f4bd2c410716b15d1951.jpg</path>
	<source>
		<database>roboflow.ai</database>
	</source>
	<size>
		<width>640</width>
		<height>640</height>
		<depth>3</depth>
	</size>
	<segmented>0</segmented>
	<object>
		<name>bike</name>
		<pose>Unspecified</pose>
		<truncated>0</truncated>
		<difficult>0</difficult>
		<occluded>0</occluded>
		<bndbox>
			<xmin>311</xmin>
			<xmax>364</xmax>
			<ymin>302</ymin>
			<ymax>444</ymax>
		</bndbox>
	</object>
</annotation>
