<annotation>
	<folder></folder>
	<filename>Navid_698_jpg.rf.a6b63f01c5c957397da69d1445d1cb9c.jpg</filename>
	<path>Navid_698_jpg.rf.a6b63f01c5c957397da69d1445d1cb9c.jpg</path>
	<source>
		<database>roboflow.ai</database>
	</source>
	<size>
		<width>640</width>
		<height>640</height>
		<depth>3</depth>
	</size>
	<segmented>0</segmented>
	<object>
		<name>vehicle</name>
		<pose>Unspecified</pose>
		<truncated>0</truncated>
		<difficult>0</difficult>
		<occluded>0</occluded>
		<bndbox>
			<xmin>113</xmin>
			<xmax>173</xmax>
			<ymin>440</ymin>
			<ymax>540</ymax>
		</bndbox>
	</object>
	<object>
		<name>bike</name>
		<pose>Unspecified</pose>
		<truncated>0</truncated>
		<difficult>0</difficult>
		<occluded>0</occluded>
		<bndbox>
			<xmin>16</xmin>
			<xmax>27</xmax>
			<ymin>464</ymin>
			<ymax>510</ymax>
		</bndbox>
	</object>
	<object>
		<name>vehicle</name>
		<pose>Unspecified</pose>
		<truncated>0</truncated>
		<difficult>0</difficult>
		<occluded>0</occluded>
		<bndbox>
			<xmin>235</xmin>
			<xmax>248</xmax>
			<ymin>461</ymin>
			<ymax>484</ymax>
		</bndbox>
	</object>
</annotation>
