<annotation>
	<folder></folder>
	<filename>Navid_493_jpg.rf.170b8d1f00cf6386d2f1c78a49763b13.jpg</filename>
	<path>Navid_493_jpg.rf.170b8d1f00cf6386d2f1c78a49763b13.jpg</path>
	<source>
		<database>roboflow.ai</database>
	</source>
	<size>
		<width>640</width>
		<height>640</height>
		<depth>3</depth>
	</size>
	<segmented>0</segmented>
	<object>
		<name>bike</name>
		<pose>Unspecified</pose>
		<truncated>0</truncated>
		<difficult>0</difficult>
		<occluded>0</occluded>
		<bndbox>
			<xmin>338</xmin>
			<xmax>414</xmax>
			<ymin>206</ymin>
			<ymax>278</ymax>
		</bndbox>
	</object>
	<object>
		<name>vehicle</name>
		<pose>Unspecified</pose>
		<truncated>0</truncated>
		<difficult>0</difficult>
		<occluded>0</occluded>
		<bndbox>
			<xmin>395</xmin>
			<xmax>432</xmax>
			<ymin>190</ymin>
			<ymax>216</ymax>
		</bndbox>
	</object>
	<object>
		<name>vehicle</name>
		<pose>Unspecified</pose>
		<truncated>0</truncated>
		<difficult>0</difficult>
		<occluded>0</occluded>
		<bndbox>
			<xmin>68</xmin>
			<xmax>109</xmax>
			<ymin>183</ymin>
			<ymax>219</ymax>
		</bndbox>
	</object>
	<object>
		<name>vehicle</name>
		<pose>Unspecified</pose>
		<truncated>0</truncated>
		<difficult>0</difficult>
		<occluded>0</occluded>
		<bndbox>
			<xmin>181</xmin>
			<xmax>213</xmax>
			<ymin>184</ymin>
			<ymax>199</ymax>
		</bndbox>
	</object>
	<object>
		<name>vehicle</name>
		<pose>Unspecified</pose>
		<truncated>0</truncated>
		<difficult>0</difficult>
		<occluded>0</occluded>
		<bndbox>
			<xmin>121</xmin>
			<xmax>144</xmax>
			<ymin>185</ymin>
			<ymax>196</ymax>
		</bndbox>
	</object>
	<object>
		<name>bike</name>
		<pose>Unspecified</pose>
		<truncated>0</truncated>
		<difficult>0</difficult>
		<occluded>0</occluded>
		<bndbox>
			<xmin>108</xmin>
			<xmax>115</xmax>
			<ymin>186</ymin>
			<ymax>194</ymax>
		</bndbox>
	</object>
</annotation>
