<annotation>
	<folder></folder>
	<filename>Numan_-216-_jpg.rf.1d6d3d38ebde36af13d80862515d320e.jpg</filename>
	<path>Numan_-216-_jpg.rf.1d6d3d38ebde36af13d80862515d320e.jpg</path>
	<source>
		<database>roboflow.ai</database>
	</source>
	<size>
		<width>640</width>
		<height>640</height>
		<depth>3</depth>
	</size>
	<segmented>0</segmented>
	<object>
		<name>vehicle</name>
		<pose>Unspecified</pose>
		<truncated>0</truncated>
		<difficult>0</difficult>
		<occluded>0</occluded>
		<bndbox>
			<xmin>177</xmin>
			<xmax>534</xmax>
			<ymin>2</ymin>
			<ymax>590</ymax>
		</bndbox>
	</object>
	<object>
		<name>vehicle</name>
		<pose>Unspecified</pose>
		<truncated>0</truncated>
		<difficult>0</difficult>
		<occluded>0</occluded>
		<bndbox>
			<xmin>112</xmin>
			<xmax>188</xmax>
			<ymin>67</ymin>
			<ymax>354</ymax>
		</bndbox>
	</object>
	<object>
		<name>vehicle</name>
		<pose>Unspecified</pose>
		<truncated>0</truncated>
		<difficult>0</difficult>
		<occluded>0</occluded>
		<bndbox>
			<xmin>61</xmin>
			<xmax>82</xmax>
			<ymin>111</ymin>
			<ymax>197</ymax>
		</bndbox>
	</object>
	<object>
		<name>vehicle</name>
		<pose>Unspecified</pose>
		<truncated>0</truncated>
		<difficult>0</difficult>
		<occluded>0</occluded>
		<bndbox>
			<xmin>3</xmin>
			<xmax>64</xmax>
			<ymin>2</ymin>
			<ymax>636</ymax>
		</bndbox>
	</object>
	<object>
		<name>vehicle</name>
		<pose>Unspecified</pose>
		<truncated>0</truncated>
		<difficult>0</difficult>
		<occluded>0</occluded>
		<bndbox>
			<xmin>87</xmin>
			<xmax>108</xmax>
			<ymin>87</ymin>
			<ymax>246</ymax>
		</bndbox>
	</object>
</annotation>
