<annotation>
	<folder></folder>
	<filename>Pias-41-_jpg.rf.c9ee1df28fc07a6866d18deeaed4f18c.jpg</filename>
	<path>Pias-41-_jpg.rf.c9ee1df28fc07a6866d18deeaed4f18c.jpg</path>
	<source>
		<database>roboflow.ai</database>
	</source>
	<size>
		<width>640</width>
		<height>640</height>
		<depth>3</depth>
	</size>
	<segmented>0</segmented>
	<object>
		<name>vehicle</name>
		<pose>Unspecified</pose>
		<truncated>0</truncated>
		<difficult>0</difficult>
		<occluded>0</occluded>
		<bndbox>
			<xmin>441</xmin>
			<xmax>623</xmax>
			<ymin>418</ymin>
			<ymax>582</ymax>
		</bndbox>
	</object>
	<object>
		<name>vehicle</name>
		<pose>Unspecified</pose>
		<truncated>0</truncated>
		<difficult>0</difficult>
		<occluded>0</occluded>
		<bndbox>
			<xmin>153</xmin>
			<xmax>268</xmax>
			<ymin>356</ymin>
			<ymax>429</ymax>
		</bndbox>
	</object>
	<object>
		<name>vehicle</name>
		<pose>Unspecified</pose>
		<truncated>0</truncated>
		<difficult>0</difficult>
		<occluded>0</occluded>
		<bndbox>
			<xmin>324</xmin>
			<xmax>365</xmax>
			<ymin>350</ymin>
			<ymax>410</ymax>
		</bndbox>
	</object>
	<object>
		<name>vehicle</name>
		<pose>Unspecified</pose>
		<truncated>0</truncated>
		<difficult>0</difficult>
		<occluded>0</occluded>
		<bndbox>
			<xmin>362</xmin>
			<xmax>412</xmax>
			<ymin>359</ymin>
			<ymax>411</ymax>
		</bndbox>
	</object>
	<object>
		<name>vehicle</name>
		<pose>Unspecified</pose>
		<truncated>0</truncated>
		<difficult>0</difficult>
		<occluded>0</occluded>
		<bndbox>
			<xmin>425</xmin>
			<xmax>469</xmax>
			<ymin>364</ymin>
			<ymax>417</ymax>
		</bndbox>
	</object>
	<object>
		<name>vehicle</name>
		<pose>Unspecified</pose>
		<truncated>0</truncated>
		<difficult>0</difficult>
		<occluded>0</occluded>
		<bndbox>
			<xmin>397</xmin>
			<xmax>427</xmax>
			<ymin>362</ymin>
			<ymax>398</ymax>
		</bndbox>
	</object>
	<object>
		<name>vehicle</name>
		<pose>Unspecified</pose>
		<truncated>0</truncated>
		<difficult>0</difficult>
		<occluded>0</occluded>
		<bndbox>
			<xmin>480</xmin>
			<xmax>497</xmax>
			<ymin>393</ymin>
			<ymax>418</ymax>
		</bndbox>
	</object>
</annotation>
